Workbook

Sheet Summary
C3: LBO Returns Summary
C5: Entry enterprise value | D5: =Assumptions!D5*Assumptions!D6 -> 200
C6: Entry debt | D6: =Assumptions!D5*Assumptions!D7 -> 125
C7: Sponsor equity | D7: =D5-D6 -> 75
C8: Exit EBITDA | D8: ='Operating Build'!I9 -> 36.733202
C9: Exit enterprise value | D9: =D8*Assumptions!D8 -> 330.59882
C10: Exit debt | D10: ='Debt Schedule'!H10 -> 29.961064
C11: Equity proceeds | D11: =D9-D10 -> 300.63775
C12: Gross MOIC | D12: =D11/D7 -> 4.0085034
C14: Gross IRR | D14: =(D11/D7)^(1/Assumptions!D9)-1 -> 0.32006845
C16: Illustrative model for deterministic Artifact OS certification. All figures are synthetic and contain no investment recommendation.

Sheet Assumptions
C3: LBO Assumptions
C5: Entry EBITDA ($m) | D5: 25
C6: Entry enterprise value / EBITDA | D6: 8
C7: Debt / EBITDA | D7: 5
C8: Exit enterprise value / EBITDA | D8: 9
C9: Hold period (years) | D9: 5
C10: Opening revenue ($m) | D10: 100
C11: Revenue growth | D11: 0.08
C12: EBITDA margin | D12: 0.25
C13: Cash conversion | D13: 0.6

Sheet Operating Build
C3: Operating Build
C5: $ in millions | D5: Entry | E5: Year 1 | F5: Year 2 | G5: Year 3 | H5: Year 4 | I5: Year 5
C7: Revenue | D7: =Assumptions!D10 -> 100 | E7: =D7*(1+Assumptions!$D$11) -> 108 | F7: =E7*(1+Assumptions!$D$11) -> 116.64 | G7: =F7*(1+Assumptions!$D$11) -> 125.9712 | H7: =G7*(1+Assumptions!$D$11) -> 136.0489 | I7: =H7*(1+Assumptions!$D$11) -> 146.93281
C8: EBITDA margin | D8: =Assumptions!D12 -> 0.25 | E8: =Assumptions!$D$12 -> 0.25 | F8: =Assumptions!$D$12 -> 0.25 | G8: =Assumptions!$D$12 -> 0.25 | H8: =Assumptions!$D$12 -> 0.25 | I8: =Assumptions!$D$12 -> 0.25
C9: EBITDA | D9: =D7*D8 -> 25 | E9: =E7*E8 -> 27 | F9: =F7*F8 -> 29.16 | G9: =G7*G8 -> 31.4928 | H9: =H7*H8 -> 34.012224 | I9: =I7*I8 -> 36.733202

Sheet Debt Schedule
C3: Debt Schedule
C5: $ in millions | D5: Year 1 | E5: Year 2 | F5: Year 3 | G5: Year 4 | H5: Year 5
C7: Opening debt | D7: =Assumptions!$D$5*Assumptions!$D$7 -> 125 | E7: =D10 -> 108.8 | F7: =E10 -> 91.304 | G7: =F10 -> 72.40832 | H7: =G10 -> 52.000986
C8: Cash available for repayment | D8: ='Operating Build'!E9*Assumptions!$D$13 -> 16.2 | E8: ='Operating Build'!F9*Assumptions!$D$13 -> 17.496 | F8: ='Operating Build'!G9*Assumptions!$D$13 -> 18.89568 | G8: ='Operating Build'!H9*Assumptions!$D$13 -> 20.407334 | H8: ='Operating Build'!I9*Assumptions!$D$13 -> 22.039921
C9: Mandatory repayment | D9: =MIN(D7,D8) -> 16.2 | E9: =MIN(E7,E8) -> 17.496 | F9: =MIN(F7,F8) -> 18.89568 | G9: =MIN(G7,G8) -> 20.407334 | H9: =MIN(H7,H8) -> 22.039921
C10: Closing debt | D10: =D7-D9 -> 108.8 | E10: =E7-E9 -> 91.304 | F10: =F7-F9 -> 72.40832 | G10: =G7-G9 -> 52.000986 | H10: =H7-H9 -> 29.961064
